stactools/chesapeake_lulc/__init__.py
stactools/chesapeake_lulc/commands.py
stactools/chesapeake_lulc/constants.py
stactools/chesapeake_lulc/fragments.py
stactools/chesapeake_lulc/metadata.py
stactools/chesapeake_lulc/stac.py
stactools/chesapeake_lulc/utils.py
stactools/chesapeake_lulc/fragments/chesapeake-lc-13/asset.json
stactools/chesapeake_lulc/fragments/chesapeake-lc-13/collection.json
stactools/chesapeake_lulc/fragments/chesapeake-lc-7/asset.json
stactools/chesapeake_lulc/fragments/chesapeake-lc-7/collection.json
stactools/chesapeake_lulc/fragments/chesapeake-lu/asset.json
stactools/chesapeake_lulc/fragments/chesapeake-lu/collection.json
stactools_chesapeake_lulc-0.1.0.dist-info/LICENSE
stactools_chesapeake_lulc-0.1.0.dist-info/METADATA
stactools_chesapeake_lulc-0.1.0.dist-info/WHEEL
stactools_chesapeake_lulc-0.1.0.dist-info/top_level.txt
stactools_chesapeake_lulc-0.1.0.dist-info/RECORD
