Metadata-Version: 2.1
Name: stactools-chesapeake-lulc
Version: 0.1.0
Summary: stactools package for Chesapeake Conservancy Land Cover and Land Use data
Home-page: https://github.com/stactools-packages/chesapeake-lulc
Author: Preston Hartzell
Author-email: preston.hartzell@gmail.com
Project-URL: Issues, https://github.com/stactools-packages/chesapeake-lulc/issues
Keywords: stactools,pystac,catalog,STAC,chesapeake,landcover
Classifier: Development Status :: 4 - Beta
Classifier: License :: OSI Approved :: Apache Software License
Classifier: Programming Language :: Python :: 3.7
Classifier: Programming Language :: Python :: 3.8
Classifier: Programming Language :: Python :: 3.9
License-File: LICENSE
Requires-Dist: stactools (>=0.2.6)
